CHANGES.txt
README.txt
bootstrap.py
buildout.cfg
conf.yaml
config.ini
demo.ini
setup.cfg
setup.py
doc/Makefile
doc/conf.py
doc/index.txt
doc/_static/favicon.ico
doc/_static/logo.jpg
doc/_static/top_bg.jpg
doc/_templates/layout.html
pyaler/__init__.py
pyaler/demo.js
pyaler/demo.py
pyaler/pyaler.py
pyaler/test_app.py
pyaler/tests.py
pyaler/tests.yaml
pyaler.egg-info/PKG-INFO
pyaler.egg-info/SOURCES.txt
pyaler.egg-info/dependency_links.txt
pyaler.egg-info/entry_points.txt
pyaler.egg-info/not-zip-safe
pyaler.egg-info/requires.txt
pyaler.egg-info/top_level.txt