Metadata-Version: 1.0
Name: pyaler
Version: 0.3
Summary: A restfull application to control your arduino devices
Home-page: http://packages.python.org/pyaler/
Author: Guyzmo, Bearstech
Author-email: bpratz@bearstech.com
License: GPLv2
Keywords: arduino http restful api
Platform: UNKNOWN
